predict_gender_ml/__init__.py
predict_gender_ml/fast_model.pth
predict_gender_ml/predict_gender.py
predict_gender_ml/vectorizer.joblib
predict_gender_ml/utils/__init__.py
predict_gender_ml/utils/gender_utils.py
predict_gender_ml-0.3.dist-info/METADATA
predict_gender_ml-0.3.dist-info/WHEEL
predict_gender_ml-0.3.dist-info/top_level.txt
predict_gender_ml-0.3.dist-info/RECORD
