Metadata-Version: 2.1
Name: predict_gender_ml
Version: 0.3
Summary: Predicts gender based on name with ML Models
Home-page: https://github.com/JumbleBumble/predict-gender-ml
Author: Jumble
Author-email: help@help.org
Classifier: License :: OSI Approved :: MIT License
Classifier: Programming Language :: Python :: 3
Classifier: Programming Language :: Python :: 3.8
Classifier: Operating System :: OS Independent
Requires-Python: >=3.8
Requires-Dist: joblib ==1.3.2
Requires-Dist: pandas ==2.1.2
Requires-Dist: torch ==2.1.0
